Metadata-Version: 2.1
Name: odoo-addon-l10n_nl_xaf_auditfile_export
Version: 18.0.1.1.0
Requires-Python: >=3.10
Requires-Dist: odoo==18.0.*
Summary: Export XAF auditfiles for Dutch tax authorities
Home-page: https://github.com/OCA/l10n-netherlands
License: AGPL-3
Author: Therp BV, Odoo Community Association (OCA)
Author-email: support@odoo-community.org
Classifier: Programming Language :: Python
Classifier: Framework :: Odoo
Classifier: Framework :: Odoo :: 18.0
Classifier: License :: OSI Approved :: GNU Affero General Public License v3
